npend/__init__.py
npend/dataType.py
npend/npend.py
npend-1.0.1.dist-info/LICENSE
npend-1.0.1.dist-info/METADATA
npend-1.0.1.dist-info/WHEEL
npend-1.0.1.dist-info/top_level.txt
npend-1.0.1.dist-info/RECORD
