Metadata-Version: 2.1
Name: npend
Version: 1.0.1
Summary: Provides a convenient way to append numpy arrays to a file.
Home-page: https://github.com/czwchenzhun/npend.git
Author: chenzhun
Author-email: 863657500@qq.com
License: UNKNOWN
Platform: UNKNOWN
Classifier: Programming Language :: Python :: 3
Classifier: License :: OSI Approved :: GNU General Public License (GPL)
Classifier: Operating System :: OS Independent
License-File: LICENSE
Requires-Dist: numpy
Requires-Dist: sip
